LICENSE
README.md
setup.py
bin/rio-generator
riocore/VERSION.py
riocore/__init__.py
riocore.egg-info/PKG-INFO
riocore.egg-info/SOURCES.txt
riocore.egg-info/dependency_links.txt
riocore.egg-info/top_level.txt
riocore/boards/Altera10M08Eval.json
riocore/boards/Arty-a7-35t.json
riocore/boards/TangNano9K.json
riocore/configs/Altera10M08Eval/config-test.json
riocore/configs/Arty-a7-35t/config-test.json
riocore/configs/Tangoboard/config-test.json
riocore/configs/Verilator/config-test.json
riocore/files/confert.py
riocore/files/debouncer.v
riocore/files/gowin-pll.py
riocore/files/hal_functions.c
riocore/files/quartus-pll.sh
riocore/files/toggle.v
riocore/generator/Gateware.py
riocore/generator/LinuxCNC.py
riocore/generator/__init__.py
riocore/generator/pins/cst/pins.py
riocore/generator/pins/lpf/pins.py
riocore/generator/pins/pcf/pins.py
riocore/generator/pins/qdf/pins.py
riocore/generator/pins/ucf/pins.py
riocore/generator/pins/xdc/pins.py
riocore/generator/toolchains/__init__.py
riocore/generator/toolchains/diamond/toolchain.py
riocore/generator/toolchains/gowin/toolchain.py
riocore/generator/toolchains/icestorm/toolchain.py
riocore/generator/toolchains/ise/toolchain.py
riocore/generator/toolchains/quartus/toolchain.py
riocore/generator/toolchains/verilator/toolchain.py
riocore/generator/toolchains/vivado/toolchain.py
riocore/interfaces/CH341/interface.py
riocore/interfaces/FTDI/interface.py
riocore/interfaces/SHM/interface.py
riocore/interfaces/SPI/interface.py
riocore/interfaces/UART/interface.c
riocore/interfaces/UART/interface.py
riocore/interfaces/UDP/interface.c
riocore/interfaces/UDP/interface.py
riocore/modules/cnc-shield-v3.json
riocore/plugins/__init__.py
riocore/plugins/ads1115/ads1115.v
riocore/plugins/ads1115/plugin.py
riocore/plugins/as5600/as5600.v
riocore/plugins/as5600/plugin.py
riocore/plugins/bitin/plugin.py
riocore/plugins/bitout/plugin.py
riocore/plugins/blink/blink.v
riocore/plugins/blink/plugin.py
riocore/plugins/counter/counter.v
riocore/plugins/counter/plugin.py
riocore/plugins/dis7seg/dis7seg.v
riocore/plugins/dis7seg/plugin.py
riocore/plugins/ds18b20/ds18b20.v
