Metadata-Version: 2.1
Name: riocore
Version: 0.0.2
Summary: riocore
Home-page: https://github.com/multigcs/LinuxCNC-RIO/
Author: Oliver Dippel
Author-email: o.dippel@gmx.de
License: LICENSE
License-File: LICENSE
